qctrlcommons/__init__.py
qctrlcommons/constants.py
qctrlcommons/core_exceptions.py
qctrlcommons/data_types.py
qctrlcommons/exceptions.py
qctrlcommons/graph.py
qctrlcommons/node/__init__.py
qctrlcommons/node/base.py
qctrlcommons/node/wrapper.py
qctrlcommons/pauli_operations.py
qctrlcommons/preconditions.py
qctrlcommons/pytest_plugin.py
qctrlcommons/run_options.py
qctrlcommons/serializers.py
qctrlcommons/utils.py
qctrl_commons-25.1.3.dist-info/LICENSE
qctrl_commons-25.1.3.dist-info/METADATA
qctrl_commons-25.1.3.dist-info/WHEEL
qctrl_commons-25.1.3.dist-info/RECORD
